verilog/div_nonrest/src/fsm_states.v
`ifndef FSM_STATES
`define FSM_STATES

`define WAITING_START 	3'b000
`define INITIALIZING  	3'b001
`define SUBTRACT 		3'b010
`define OUTBUS_A		3'b011
`define OUTBUS_Q		3'b100
`define DONE			3'b101

`endif

verilog/div_rest/src/divrest.v
`include "src/fsm_states.v"
module divrest
	( 
		M,
		Q,
		clk,
		start,
		reset,
		outbus,
		busy
	
	);
	
	input 		[7:0] 	M;
	input 		[7:0] 	Q;
	input 			clk;
	input 			start;
	input			reset;
	output reg 	[7:0]	outbus;
	output			busy;
	
	
	
  reg 		[2:0] 	counter;
	
	reg 		[2:0] 	current_state;
	reg		[2:0]	next_state;
	
  	reg 		[16:0] 	AQ;
	
	reg 		[8:0] 	M1;
	
	reg 		[8:0] 	sum;
	
	always @(start,counter,current_state)
	begin
		case (current_state)
			`WAITING_START: begin
				if (start) begin
					next_state<=`INITIALIZING;
				end	
			end
			`INITIALIZING: begin
				next_state<=`SUBTRACT;
			end
			`SUBTRACT: begin
              if(counter==3'b111) begin
					next_state<=`OUTBUS_Q;
				end
			end
			`OUTBUS_Q: begin
				next_state<=`OUTBUS_A;
			end
			`OUTBUS_A:begin
				next_state<=`DONE;
			end
			`DONE:;
			default: next_state<=`INITIALIZING;
		endcase
	end		
			
	always @(posedge clk or posedge reset)
	begin
		if(reset) begin
			current_state<=`WAITING_START;
		end
		else begin
			current_state<=next_state;
		end
	end
	

	always @(posedge clk) begin
		case (current_state)
			`WAITING_START: ;
			`INITIALIZING: begin
				//initialize A with zeroes
              	AQ[16:8]<=9'b0;
				//get Q from inbus;
              	AQ[7:0]<=Q;
				//initialize counter
				counter<=3'b000;
				//initialize Q[-1]
				M1<={M[7],M};
              	
			end
			`SUBTRACT: begin
				//actually shift AQ register;
             
				//AQ<=AQ<<1;
              	AQ<={AQ[15:1],1'b0};
	            AQ<=AQ[16:8]-M1;
              	if(AQ[16]==0) begin
                  AQ[0]=1'b1;
                end
              	else begin
                  AQ[0]=1'b0;
                  AQ<=AQ[16:8]+M1;
                end
              $display(" Count %d A %b\t Q %b\n M %b",counter,AQ[16:7],AQ[7:0],M1);
				counter<=counter+3'b001;
			end
			`OUTBUS_A: begin
              	outbus<=AQ[15:8];
			end
			`OUTBUS_Q: begin
              outbus<=AQ[7:0];
			end
			`DONE: ;
		endcase
	end
	
	
	assign busy = (current_state != `DONE && current_state!=`WAITING_START) ? 1'b1:1'b0;
endmodule

verilog/div_rest/testbench/divrest_tb.v
`timescale 1 ns/1 ps
`define assert_eq(signal, value) \
	if (signal !== value) begin \
   		$display("ASSERTION FAILED in %m: signal != value"); \
   		$finish; \
	end

module divrest_tb;
	reg clk;
	reg reset;
	reg start;
    
	wire busy;
  	reg [7:0] M;
  	reg [7:0] Q;

  	wire  [7:0] outbus;

	divrest mod(
		.clk(clk),.reset(reset),.start(start),.busy(busy),
      .M(M),.Q(Q),.outbus(outbus)
	);
	
	always begin
		#5 clk=!clk;
	end
	
	initial begin
      	$dumpfile("divrest.vcd"); $dumpvars;
		clk<=0;
      	#25 reset<=1;
      	#25 reset<=0;
      	#10 start<=1;
	  	#5 M<=8'b00000100;
       	Q<=8'b00001110;
	
    	#1000
		$finish;

	end
	

endmodule

verilog/div_rest/divrest.vcd
$date
	Mon Mar 26 22:17:48 2018
$end
$version
	Icarus Verilog
$end
$timescale
	1ps
$end
$scope module divrest_tb $end
$var wire 8 ! outbus [7:0] $end
$var wire 1 " busy $end
$var reg 8 # M [7:0] $end
$var reg 8 $ Q [7:0] $end
$var reg 1 % clk $end
$var reg 1 & reset $end
$var reg 1 ' start $end
$scope module mod $end
$var wire 8 ( M [7:0] $end
$var wire 8 ) Q [7:0] $end
$var wire 1 % clk $end
$var wire 1 & reset $end
$var wire 1 ' start $end
$var wire 1 " busy $end
$var reg 17 * AQ [16:0] $end
$var reg 9 + M1 [8:0] $end
$var reg 3 , counter [2:0] $end
$var reg 3 - current_state [2:0] $end
$var reg 3 . next_state [2:0] $end
$var reg 8 / outbus [7:0] $end
$upscope $end
$upscope $end
$enddefinitions $end
#0
$dumpvars
bx /
bx .
bx -
bx ,
bx +
bx *
bx )
bx (
x'
x&
0%
bx $
bx #
x"
bx !
$end
#5000
1%
#10000
0%
#15000
1%
#20000
0%
#25000
0"
b0 -
1&
1%
#30000
0%
#35000
1%
#40000
0%
#45000
1%
#50000
0&
0%
#55000
b1 .
x"
bx -
1%
#60000
1'
0%
#65000
b10 .
1"
b1 -
b1110 $
b1110 )
b100 #
b100 (
1%
#70000
0%
#75000
b100 +
b0 ,
b1110 *
b10 -
1%
#80000
0%
#85000
b1 ,
b11111111111111100 *
1%
#90000
0%
#95000
b10 ,
b1000000011 *
1%
#100000
0%
#105000
b11 ,
b11111111111111110 *
1%
#110000
0%
#115000
b100 ,
b1000000011 *
1%
#120000
0%
#125000
b101 ,
b11111111111111110 *
1%
#130000
0%
#135000
b110 ,
b1000000011 *
1%
#140000
0%
#145000
b100 .
b111 ,
b11111111111111110 *
1%
#150000
0%
#155000
b11 .
b0 ,
b1000000011 *
b100 -
1%
#160000
0%
#165000
b101 .
b11 !
b11 /
b11 -
1%
#170000
0%
#175000
0"
b10 !
b10 /
b101 -
1%
