verilog/counter/src/counter.v
//----------------------------------------------
// Design Name: 8 bit up/down counter with load
// File Name: counter.v
// Function: Up/Down counter
// Coder: Mihai
//----------------------------------------------

module counter(
	       out,//counter output
	       up_down,//up_down control
	       clk,//clock input
	       data,//data to load
	       load,//load data
	       enable,//enable counting
	       reset//reset input
	       );
   //-----Output Ports-----
   output[7:0] out;
   //-----Input Ports-----
   input [7:0] data;
   input      up_down,clk,reset,load,enable;
   reg [7:0]  out;
   reg [7:0] data_buf;
   
   
   always @(posedge clk) begin
      if(reset) begin
	 out<=8'b0;
      end
      if (load) begin
	 out<=data;
      end  
      if(enable) begin
	 if(up_down && out<data) begin //if updown=1, count up
	    out<=out+1;
	 end 
	 if(~up_down && out>0) begin //updown=0, count down
	    out<=out-1;
	 end
      end
   end
endmodule

verilog/counter/testbench/counter_tb.v
`timescale 1 ns/1 ps
`define assert_eq(signal, value) \
if (signal !== value) begin \
   $display("ASSERTION FAILED in %m: signal != value"); \
   $finish; \
end
module counter_tb;
   reg [7:0] data_t;
   wire [7:0]  out_t;
   reg 	      clk_t,reset_t,up_down_t,load_t,enable_t;
   counter c0(
	      .out(out_t),
	      .up_down(up_down_t),
	      .clk(clk_t),
	      .data(data_t),
	      .load(load_t),
	      .enable(enable_t),
	      .reset(reset_t)
	      );
  
  always  #1 clk_t=!clk_t;
   
   initial begin
      clk_t=0;
      $dumpfile("counter.vcd");
      $dumpvars;
      
      //Test 1: cout up
      reset_t=1;
      
      #5 data_t='h0F;
      #5 up_down_t=1;
       `assert_eq(out_t,0);
      #5 enable_t=1;
      #1 `assert_eq(out_t,1);
      #2 `assert_eq(out_t,2);
      #2 `assert_eq(out_t,3);
      #2 `assert_eq(out_t,4);
      #2 `assert_eq(out_t,5);
      #2 `assert_eq(out_t,6);
      #2 `assert_eq(out_t,7);
      #2 `assert_eq(out_t,8);
      #2 `assert_eq(out_t,9);
      #2 `assert_eq(out_t,'h0A);
      #2 `assert_eq(out_t,'h0B);
      #2 `assert_eq(out_t,'h0C);
      #2 `assert_eq(out_t,'h0D);
      #2 `assert_eq(out_t,'h0E);
      #2 `assert_eq(out_t,'h0F);
      enable_t=0;
      
      //Test 2
       reset_t=1;
      #5 data_t='h0F;
      #5 load_t=1;
      #5 up_down_t=0;
      `assert_eq(out_t,'h0F);
      #5 enable_t=1;
      #2 `assert_eq(out_t,'h0E);
      #2 `assert_eq(out_t,'h0D);
      #2 `assert_eq(out_t,'h0C);
      #2 `assert_eq(out_t,'h0B);
      #2 `assert_eq(out_t,'h0A);
      #2 `assert_eq(out_t,9);
      #2 `assert_eq(out_t,8);
      #2 `assert_eq(out_t,7);
      #2 `assert_eq(out_t,6);
      #2 `assert_eq(out_t,5);
      #2 `assert_eq(out_t,4);
      #2 `assert_eq(out_t,3);
      #2 `assert_eq(out_t,2);
      #2 `assert_eq(out_t,1);
      #2 `assert_eq(out_t,0);
      $finish;
      
   end
   initial begin
      $display("\t\ttime,\tdata,\tclk,\tup_down,\treset,\tload,\tenable,\tout");
      $monitor("%d,\t%b,\t%b,\t%b,\t%b,\t%b,\t%b,\t%b",
	       $time,data_t,clk_t,up_down_t,reset_t,load_t,enable_t,out_t);
      
   end
   
   




endmodule

verilog/counter/obj/counter.vcd
$date
	Sun Mar  4 13:40:02 2018
$end
$version
	Icarus Verilog
$end
$timescale
	1ps
$end
$scope module counter_tb $end
$var wire 8 ! out_t [7:0] $end
$var reg 1 " clk_t $end
$var reg 8 # data_t [7:0] $end
$var reg 1 $ enable_t $end
$var reg 1 % load_t $end
$var reg 1 & reset_t $end
$var reg 1 ' up_down_t $end
$scope module c0 $end
$var wire 1 " clk $end
$var wire 8 ( data [7:0] $end
$var wire 1 $ enable $end
$var wire 1 % load $end
$var wire 1 & reset $end
$var wire 1 ' up_down $end
$var reg 8 ) out [7:0] $end
$upscope $end
$upscope $end
$enddefinitions $end
#0
$dumpvars
bx )
bx (
x'
1&
x%
x$
bx #
0"
bx !
$end
#1000
b0 !
b0 )
1"
#2000
0"
#3000
1"
#4000
0"
#5000
1"
b1111 #
b1111 (
#6000
0"
#7000
1"
#8000
0"
#9000
1"
#10000
0"
1'
#11000
1"
#12000
0"
#13000
1"
#14000
0"
#15000
b1 !
b1 )
1"
1$
#16000
0"
#17000
b10 !
b10 )
1"
#18000
0"
#19000
b11 !
b11 )
1"
#20000
0"
#21000
b100 !
b100 )
1"
#22000
0"
#23000
b101 !
b101 )
1"
#24000
0"
#25000
b110 !
b110 )
1"
#26000
0"
#27000
b111 !
b111 )
1"
#28000
0"
#29000
b1000 !
b1000 )
1"
#30000
0"
#31000
b1001 !
b1001 )
1"
#32000
0"
#33000
b1010 !
b1010 )
1"
#34000
0"
#35000
b1011 !
b1011 )
1"
#36000
0"
#37000
b1100 !
b1100 )
1"
#38000
0"
#39000
b1101 !
b1101 )
1"
#40000
0"
#41000
b1110 !
b1110 )
1"
#42000
0"
#43000
b1111 !
b1111 )
1"
#44000
0"
0$
#45000
b0 !
b0 )
1"
#46000
0"
#47000
1"
#48000
0"
#49000
1"
#50000
0"
#51000
1"
#52000
0"
#53000
1"
#54000
0"
1%
#55000
b1111 !
b1111 )
1"
#56000
0"
#57000
b1111 !
b1111 )
1"
#58000
0"
#59000
b1111 !
b1111 )
1"
0'
#60000
0"
#61000
b1111 !
b1111 )
1"
#62000
0"
#63000
b1111 !
b1111 )
1"
#64000
0"
1$
#65000
b1110 !
b1110 )
1"
#66000
0"
#67000
b1101 !
b1101 )
1"
#68000
0"
#69000
b1100 !
b1100 )
1"
#70000
0"
#71000
b1011 !
b1011 )
1"
#72000
0"
#73000
b1010 !
b1010 )
1"
#74000
0"
#75000
b1001 !
b1001 )
1"
#76000
0"
#77000
b1000 !
b1000 )
1"
#78000
0"
#79000
b111 !
b111 )
1"
#80000
0"
#81000
b110 !
b110 )
1"
#82000
0"
#83000
b101 !
b101 )
1"
#84000
0"
#85000
b100 !
b100 )
1"
#86000
0"
#87000
b11 !
b11 )
1"
#88000
0"
#89000
b10 !
b10 )
1"
#90000
0"
#91000
b1 !
b1 )
1"
#92000
0"
#93000
b0 !
b0 )
1"
