verilog/7_seg_decoder/testbench/test_inc.v
`ifndef TEST_INCLUDE_V
`define TEST_INCLUDE_V

`define assert(signal, value) \
if (signal !== value) begin \
   $display("ASSERTION FAILED in %m: signal != value"); \
   $finish; \
end


`endif

verilog/7_seg_decoder/src/drv_7seg.v
//----------------------------------------------
// Design Name: Common Cathode 7-segments display driver
// File Name: drv_7seg.v
// Function: Driver used for lamp test
// Developer: Mihai
//----------------------------------------------
module drv_7seg(
    lt,
    inbus,
    outbus
    );

    input               lt;
    input       [7:0]   inbus;
    output  reg [7:0]   outbus;

    always @(lt,inbus) begin : drv_7seg
        if(lt) begin
            outbus<=inbus;
        end else begin
            outbus<=8'b11111111; 
        end
    end

endmodule // drv_7seg

verilog/7_seg_decoder/src/dec_7seg.v
//----------------------------------------------
// Design Name: Common Cathode 7-segments display driver
// File Name: dec_7seg.v
// Function: BCD-to-7 segments decoder ( 0-9)
// Developer: Mihai
//----------------------------------------------

module dec_7seg(
    datain,
    bl,
    dataout
    );

    input   [3:0]   datain; 
    input           bl;
    output  [7:0]   dataout;
    




    assign dataout[7]=(bl==1'b0)?8'b00000000:(datain[3]&(~datain[2])&(~datain[1]))|
                ((~datain[3])&(datain[1]|(((~datain[2])&(~datain[0]))|(datain[2]&datain[0]))));


    assign dataout[6]=(bl==1'b0)?8'b00000000:((~(datain[3]&datain[1]))&(~datain[2]))|
                        ((~datain[3])&((datain[1]&datain[0])|((~datain[1])&(~datain[0]))));


    assign dataout[5]=(bl==1'b0)?8'b00000000:((~datain[2])&(~datain[1]))|
                        ((~datain[3])&(datain[2]|datain[0]));

    
    assign dataout[4]=(bl==1'b0)?8'b00000000:
                ((~datain[3])&(~datain[2])&(datain[1]|(~datain[0])))|
                ((~datain[3])&((datain[1]&(~datain[0]))|(datain[2]&datain[0]&(~datain[1]))))|
                (datain[3]&(~datain[2])&(~datain[1]));


    
    assign dataout[3]=(bl==1'b0)?8'b00000000:
                (~datain[0])&(((~datain[2])&(~datain[1]))|((~datain[3])&datain[1]));


    assign dataout[2]=(bl==1'b0)?8'b00000000:
        ((~datain[3])&((datain[2]&(~(datain[1]&datain[0])))|((~datain[1])&(~datain[0]))))|
        (datain[3]&(~datain[2])&(~datain[1]));

    assign dataout[1]=(bl==1'b0)?8'b00000000:
            ((~datain[3])&((datain[1]&(~(datain[2]&datain[0])))|(datain[2]&(~datain[1]))))|
            (datain[3]&(~datain[2])&(~datain[1]));


    assign dataout[0]=1'b0;//dot



endmodule // decoder

verilog/7_seg_decoder/src/dlatch.v
//----------------------------------------------
// Design Name: Common Cathode 7-segments display driver
// File Name: dlatch.v
// Function: D-type Latch
// Developer: Mihai
//----------------------------------------------

module dlatch(
    d,
    q,
    nq,
    ena,
    nena
    );
    
    input       d;
    input       ena;
    input       nena;
    output  reg q;
    output  reg nq;

    always @(d,ena,nena) begin: d_latch_procedure
        if(ena) begin
            q<=d;
            nq<=~d;
        end // if( le='1')
        else begin
        end

    end // d_latch_procedure

    



endmodule // dlatch

verilog/7_seg_decoder/src/driver_7_segments.v
//----------------------------------------------
// Design Name: Common Cathode 7-segments display driver
// File Name: driver_7_segments.v
// Function: 7-segments display driver
// Developer: Mihai
//----------------------------------------------



module driver_7_segments(
    inbus,
    le,
    lt,
    bl,
    outbus,

    );
    
    input       [3:0]   inbus;      //input data
    input               le;             //latch-enable
    input               lt;             //lamp-test->displays 8
    input               bl;             //blanking-> blank
    output reg  [7:0]   outbus;


    wire [3:0]  latch_output;
    wire [7:0]  decoder_output;

    dlatch latch0(
        .d  (inbus[0]),
        .ena (~le),
        .nena(le),
        .q  (latch_output[0]),
        .nq ()
        );
    
    dlatch latch1(
        .d  (inbus[1]),
        .ena (~le),
        .nena(le),
        .q  (latch_output[1]),
        .nq ()
        );
    
    dlatch latch2(
        .d  (inbus[2]),
        .ena (~le),
        .nena(le),
        .q  (latch_output[2]),
        .nq ()
        );

    dlatch latch3(
        .d  (inbus[3]),
        .ena (~le),
        .nena(le),
        .q  (latch_output[3]),
        .nq ()
        );
    dec_7seg decoder_7_segments(
        .datain (latch_output),
        .bl     (bl),
        .dataout(decoder_output)
        );
    
    drv_7seg driver_7_segments(
        .inbus (decoder_output),
        .lt    (lt),
        .outbus(outbus)
        );

    
    
endmodule // segments_driver

verilog/7_seg_decoder/testbench/driver_7_segments_tb.v
`include "testbench/test_inc.v"
module driver_7_segments_tb;

	reg       [3:0]   inbus;      //input data
    reg               le;             //latch-enable
    reg               lt;             //lamp-test->displays 8
    reg               bl;             //blanking-> blank
    wire reg  [7:0]   outbus;

    driver_7_segments driver(
    	.inbus (inbus),
    	.le    (le),
    	.lt    (lt),
    	.bl    (bl),
    	.outbus(outbus)
    	);

    initial begin
        $dumpfile("segments_driver_tb.vcd");
        $dumpvars;

        //Lamp Test
        le<=1'b0;//latch is transparent
        bl<=1'b1;//blanking is disabled
        inbus<=4'b0000;//0 on inbus
        lt<=1'b0;//lamp test enabled
        #25
        `assert(outbus,8'b11111111);

        #50
        //Blanking Test
        le<=1'b0;//latch is transparent
        bl<=1'b0;//blanking is enabled
		inbus<=4'b0000;//0 on inbus
        lt<=1'b1;//lamp test disabled
        #25
        `assert(outbus,8'b00000000);        

        #50
        //test all values
        le<=1'b0;//latch is transparent
        bl<=1'b1;//blanking is disabled
        lt<=1'b1; //lamp test is disabled
        
        #25
        inbus<=4'b0000;
        #25
        `assert(outbus,8'b11111100);
		
		#25
        inbus<=4'b0001;
        #25
        `assert(outbus,8'b01100000);

		#25
        inbus<=4'b0010;
        #25
        `assert(outbus,8'b11011010);

        #25
        inbus<=4'b0011;
        #25
        `assert(outbus,8'b11110010);

        #25
        inbus<=4'b0100;
        #25
        `assert(outbus,8'b01100110);

        #25
        inbus<=4'b0101;
        #25
        `assert(outbus,8'b10110110);

        #25
        inbus<=4'b0110;
        #25
        `assert(outbus,8'b10111110);

        #25
        inbus<=4'b0111;
        #25
        `assert(outbus,8'b11100000);

        #25
        inbus<=4'b1000;
        #25
        `assert(outbus,8'b11111110);

        #25
        inbus<=4'b1001;
        #25
        `assert(outbus,8'b11110110);


    end // initial


    initial begin :dump_proc
            $display("\t\tTime\tINBUS\t/LE\t/LT\t/BL\tOUTBUS");
            $monitor("%d\t%b\t%b\t%b\t%b\t%b",$time,inbus,le,lt,bl,outbus);
    end // dump_proc
endmodule // segments_driver_tb

verilog/7_seg_decoder/segments_driver_tb.vcd
$date
	Mon Apr  9 16:39:01 2018
$end
$version
	Icarus Verilog
$end
$timescale
	1s
$end
$scope module driver_7_segments_tb $end
$var wire 8 ! outbus [7:0] $end
$var reg 1 " bl $end
$var reg 4 # inbus [3:0] $end
$var reg 1 $ le $end
$var reg 1 % lt $end
$scope module driver $end
$var wire 1 " bl $end
$var wire 4 & inbus [3:0] $end
$var wire 1 $ le $end
$var wire 1 % lt $end
$var wire 8 ' outbus [7:0] $end
$var wire 4 ( latch_output [3:0] $end
$var wire 8 ) decoder_output [7:0] $end
$scope module decoder_7_segments $end
$var wire 1 " bl $end
$var wire 4 * datain [3:0] $end
$var wire 8 + dataout [7:0] $end
$upscope $end
$scope module driver_7_segments $end
$var wire 8 , inbus [7:0] $end
$var wire 1 % lt $end
$var reg 8 - outbus [7:0] $end
$scope begin drv_7seg $end
$upscope $end
$upscope $end
$scope module latch0 $end
$var wire 1 . d $end
$var wire 1 / ena $end
$var wire 1 $ nena $end
$var reg 1 0 nq $end
$var reg 1 1 q $end
$scope begin d_latch_procedure $end
$upscope $end
$upscope $end
$scope module latch1 $end
$var wire 1 2 d $end
$var wire 1 3 ena $end
$var wire 1 $ nena $end
$var reg 1 4 nq $end
$var reg 1 5 q $end
$scope begin d_latch_procedure $end
$upscope $end
$upscope $end
$scope module latch2 $end
$var wire 1 6 d $end
$var wire 1 7 ena $end
$var wire 1 $ nena $end
$var reg 1 8 nq $end
$var reg 1 9 q $end
$scope begin d_latch_procedure $end
$upscope $end
$upscope $end
$scope module latch3 $end
$var wire 1 : d $end
$var wire 1 ; ena $end
$var wire 1 $ nena $end
$var reg 1 < nq $end
$var reg 1 = q $end
$scope begin d_latch_procedure $end
$upscope $end
$upscope $end
$upscope $end
$scope begin dump_proc $end
$upscope $end
$upscope $end
$enddefinitions $end
#0
$dumpvars
0=
1<
1;
0:
09
18
17
06
05
14
13
02
01
10
1/
0.
b11111111 -
b11111100 ,
b11111100 +
b0 *
b11111100 )
b0 (
b11111111 '
b0 &
0%
0$
b0 #
1"
b11111111 !
$end
#75
b0 !
b0 '
b0 -
b0 )
b0 +
b0 ,
1%
0"
#150
b11111100 !
b11111100 '
b11111100 -
b11111100 )
b11111100 +
b11111100 ,
1"
#225
b1100000 !
b1100000 '
b1100000 -
b1100000 )
b1100000 +
b1100000 ,
00
b1 (
b1 *
11
1.
b1 #
b1 &
#275
b11011010 !
b11011010 '
b11011010 -
b11011010 )
b11011010 +
b11011010 ,
10
01
04
b10 (
b10 *
15
0.
12
b10 #
b10 &
#325
b11110010 !
b11110010 '
b11110010 -
b11110010 )
b11110010 +
b11110010 ,
00
b11 (
b11 *
11
1.
b11 #
b11 &
#375
b1100110 !
b1100110 '
b1100110 -
b1100110 )
b1100110 +
b1100110 ,
10
01
14
05
08
b100 (
b100 *
19
0.
02
16
b100 #
b100 &
#425
b10110110 !
b10110110 '
b10110110 -
b10110110 )
b10110110 +
b10110110 ,
00
b101 (
b101 *
11
1.
b101 #
b101 &
#475
b10111110 !
b10111110 '
b10111110 -
b10111110 )
b10111110 +
b10111110 ,
10
01
04
b110 (
b110 *
15
0.
12
b110 #
b110 &
#525
b11100000 !
b11100000 '
b11100000 -
b11100000 )
b11100000 +
b11100000 ,
00
b111 (
b111 *
11
1.
b111 #
b111 &
#575
b11111110 !
b11111110 '
b11111110 -
b11111110 )
b11111110 +
b11111110 ,
10
01
14
05
18
09
0<
b1000 (
b1000 *
1=
0.
02
06
1:
b1000 #
b1000 &
#625
b11110110 !
b11110110 '
b11110110 -
b11110110 )
b11110110 +
b11110110 ,
00
b1001 (
b1001 *
11
1.
b1001 #
b1001 &
