verilog/counter_4_bit/src/d_ff.v
//----------------------------------------------
// Design Name: D Flip Flop 
// File Name: d_ff.v
// Function: D Flip Flop
// Developer: Mihai
//----------------------------------------------
module d_ff(data,clk,reset,q,qn);
	
	input data,clk,reset;
	output reg q;
	output reg qn;
	
	
	always @(posedge clk)
		if(reset) begin
			q<=1'b0;
			qn<=1'b1;
		end else begin
			q<=data;
			qn<=~data;
		end
endmodule

verilog/freq_divider/src/freq_div.v
//----------------------------------------------
// Design Name: Divide by 2 Counter
// File Name: frequencydivider.v
// Function: Frequency divider by 2
// Developer: Mihai
//----------------------------------------------
module freq_div(
	clk, frequency,reset);
	input clk;
	input reset;
	output frequency;

	wire feedback_loop;

	d_ff d_flipflop(.data(feedback_loop),.clk(clk),.reset(reset),.q(frequency),.qn(feedback_loop));
endmodule // frequencydivider

verilog/freq_divider/testbench/freq_div_tb.v
`define assert(signal, value) \
if (signal !== value) begin \
   $display("ASSERTION FAILED in %m: signal != value"); \
   $finish; \
end
module freq_div_tb;
   wire f_t;
   
   reg clk_t,reset_t;
   
   freq_div div(.frequency(f_t),.clk(clk_t),.reset(reset_t));
   
   always begin
      #1 clk_t=!clk_t;
   end
   initial begin
      clk_t=0;
      $dumpfile("freq_div.vcd");
      $dumpvars;
      
      //Test 1: reset=1, d!=0=>q=0
      reset_t=1'b1;
      
      #5 reset_t=1'b0;
      	//`assert(f_t,1);
      #1000 reset_t=1'b1;
      
	
      
      $finish;
      
   end
   initial begin
      $display("\t\ttime,\tclk,\treset,\tf");
      $monitor("%d,\t%b,\t%b,\t%b",$time,clk_t,reset_t,f_t);
      
   end
   
   




endmodule

verilog/freq_divider/obj/freq_div.vcd
$date
	Wed Mar  7 23:34:07 2018
$end
$version
	Icarus Verilog
$end
$timescale
	1s
$end
$scope module freq_div_tb $end
$var wire 1 ! f_t $end
$var reg 1 " clk_t $end
$var reg 1 # reset_t $end
$scope module div $end
$var wire 1 " clk $end
$var wire 1 # reset $end
$var wire 1 ! frequency $end
$var wire 1 $ feedback_loop $end
$scope module d_flipflop $end
$var wire 1 " clk $end
$var wire 1 # reset $end
$var wire 1 $ data $end
$var reg 1 ! q $end
$var reg 1 $ qn $end
$upscope $end
$upscope $end
$upscope $end
$enddefinitions $end
#0
$dumpvars
x$
1#
0"
x!
$end
#1
1$
0!
1"
#2
0"
#3
1"
#4
0"
#5
0$
1!
1"
0#
#6
0"
#7
1$
0!
1"
#8
0"
#9
0$
1!
1"
#10
0"
#11
1$
0!
1"
#12
0"
#13
0$
1!
1"
#14
0"
#15
1$
0!
1"
#16
0"
#17
0$
1!
1"
#18
0"
#19
1$
0!
1"
#20
0"
#21
0$
1!
1"
#22
0"
#23
1$
0!
1"
#24
0"
#25
0$
1!
1"
#26
0"
#27
1$
0!
1"
#28
0"
#29
0$
1!
1"
#30
0"
#31
1$
0!
1"
#32
0"
#33
0$
1!
1"
#34
0"
#35
1$
0!
1"
#36
0"
#37
0$
1!
1"
#38
0"
#39
1$
0!
1"
#40
0"
#41
0$
1!
1"
#42
0"
#43
1$
0!
1"
#44
0"
#45
0$
1!
1"
#46
0"
#47
1$
0!
1"
#48
0"
#49
0$
1!
1"
#50
0"
#51
1$
0!
1"
#52
0"
#53
0$
1!
1"
#54
0"
#55
1$
0!
1"
#56
0"
#57
0$
1!
1"
#58
0"
#59
1$
0!
1"
#60
0"
#61
0$
1!
1"
#62
0"
#63
1$
0!
1"
#64
0"
#65
0$
1!
1"
#66
0"
#67
1$
0!
1"
#68
0"
#69
0$
1!
1"
#70
0"
#71
1$
0!
1"
#72
0"
#73
0$
1!
1"
#74
0"
#75
1$
0!
1"
#76
0"
#77
0$
1!
1"
#78
0"
#79
1$
0!
1"
#80
0"
#81
0$
1!
1"
#82
0"
#83
1$
0!
1"
#84
0"
#85
0$
1!
1"
#86
0"
#87
1$
0!
1"
#88
0"
#89
0$
1!
1"
#90
0"
#91
1$
0!
1"
#92
0"
#93
0$
1!
1"
#94
0"
#95
1$
0!
1"
#96
0"
#97
0$
1!
1"
#98
0"
#99
1$
0!
1"
#100
0"
#101
0$
1!
1"
#102
0"
#103
1$
0!
1"
#104
0"
#105
0$
1!
1"
#106
0"
#107
1$
0!
1"
#108
0"
#109
0$
1!
1"
#110
0"
#111
1$
0!
1"
#112
0"
#113
0$
1!
1"
#114
0"
#115
1$
0!
1"
#116
0"
#117
0$
1!
1"
#118
0"
#119
1$
0!
1"
#120
0"
#121
0$
1!
1"
#122
0"
#123
1$
0!
1"
#124
0"
#125
0$
1!
1"
#126
0"
#127
1$
0!
1"
#128
0"
#129
0$
1!
1"
#130
0"
#131
1$
0!
1"
#132
0"
#133
0$
1!
1"
#134
0"
#135
1$
0!
1"
#136
0"
#137
0$
1!
1"
#138
0"
#139
1$
0!
1"
#140
0"
#141
0$
1!
1"
#142
0"
#143
1$
0!
1"
#144
0"
#145
0$
1!
1"
#146
0"
#147
1$
0!
1"
#148
0"
#149
0$
1!
1"
#150
0"
#151
1$
0!
1"
#152
0"
#153
0$
1!
1"
#154
0"
#155
1$
0!
1"
#156
0"
#157
0$
1!
1"
#158
0"
#159
1$
0!
1"
#160
0"
#161
0$
1!
1"
#162
0"
#163
1$
0!
1"
#164
0"
#165
0$
1!
1"
#166
0"
#167
1$
0!
1"
#168
0"
#169
0$
1!
1"
#170
0"
#171
1$
0!
1"
#172
0"
#173
0$
1!
1"
#174
0"
#175
1$
0!
1"
#176
0"
#177
0$
1!
1"
#178
0"
#179
1$
0!
1"
#180
0"
#181
0$
1!
1"
#182
0"
#183
1$
0!
1"
#184
0"
#185
0$
1!
1"
#186
0"
#187
1$
0!
1"
#188
0"
#189
0$
1!
1"
#190
0"
#191
1$
0!
1"
#192
0"
#193
0$
1!
1"
#194
0"
#195
1$
0!
1"
#196
0"
#197
0$
1!
1"
#198
0"
#199
1$
0!
1"
#200
0"
#201
0$
1!
1"
#202
0"
#203
1$
0!
1"
#204
0"
#205
0$
1!
1"
#206
0"
#207
1$
0!
1"
#208
0"
#209
0$
1!
1"
#210
0"
#211
1$
0!
1"
#212
0"
#213
0$
1!
1"
#214
0"
#215
1$
0!
1"
#216
0"
#217
0$
1!
1"
#218
0"
#219
1$
0!
1"
#220
0"
#221
0$
1!
1"
#222
0"
#223
1$
0!
1"
#224
0"
#225
0$
1!
1"
#226
0"
#227
1$
0!
1"
#228
0"
#229
0$
1!
1"
#230
0"
#231
1$
0!
1"
#232
0"
#233
0$
1!
1"
#234
0"
#235
1$
0!
1"
#236
0"
#237
0$
1!
1"
#238
0"
#239
1$
0!
1"
#240
0"
#241
0$
1!
1"
#242
0"
#243
1$
0!
1"
#244
0"
#245
0$
1!
1"
#246
0"
#247
1$
0!
1"
#248
0"
#249
0$
1!
1"
#250
0"
#251
1$
0!
1"
#252
0"
#253
0$
1!
1"
#254
0"
#255
1$
0!
1"
#256
0"
#257
0$
1!
1"
#258
0"
#259
1$
0!
1"
#260
0"
#261
0$
1!
1"
#262
0"
#263
1$
0!
1"
#264
0"
#265
0$
1!
1"
#266
0"
#267
1$
0!
1"
#268
0"
#269
0$
1!
1"
#270
0"
#271
1$
0!
1"
#272
0"
#273
0$
1!
1"
#274
0"
#275
1$
0!
1"
#276
0"
#277
0$
1!
1"
#278
0"
#279
1$
0!
1"
#280
0"
#281
0$
1!
1"
#282
0"
#283
1$
0!
1"
#284
0"
#285
0$
1!
1"
#286
0"
#287
1$
0!
1"
#288
0"
#289
0$
1!
1"
#290
0"
#291
1$
0!
1"
#292
0"
#293
0$
1!
1"
#294
0"
#295
1$
0!
1"
#296
0"
#297
0$
1!
1"
#298
0"
#299
1$
0!
1"
#300
0"
#301
0$
1!
1"
#302
0"
#303
1$
0!
1"
#304
0"
#305
0$
1!
1"
#306
0"
#307
1$
0!
1"
#308
0"
#309
0$
1!
1"
#310
0"
#311
1$
0!
1"
#312
0"
#313
0$
1!
1"
#314
0"
#315
1$
0!
1"
#316
0"
#317
0$
1!
1"
#318
0"
#319
1$
0!
1"
#320
0"
#321
0$
1!
1"
#322
0"
#323
1$
0!
1"
#324
0"
#325
0$
1!
1"
#326
0"
#327
1$
0!
1"
#328
0"
#329
0$
1!
1"
#330
0"
#331
1$
0!
1"
#332
0"
#333
0$
1!
1"
#334
0"
#335
1$
0!
1"
#336
0"
#337
0$
1!
1"
#338
0"
#339
1$
0!
1"
#340
0"
#341
0$
1!
1"
#342
0"
#343
1$
0!
1"
#344
0"
#345
0$
1!
1"
#346
0"
#347
1$
0!
1"
#348
0"
#349
0$
1!
1"
#350
0"
#351
1$
0!
1"
#352
0"
#353
0$
1!
1"
#354
0"
#355
1$
0!
1"
#356
0"
#357
0$
1!
1"
#358
0"
#359
1$
0!
1"
#360
0"
#361
0$
1!
1"
#362
0"
#363
1$
0!
1"
#364
0"
#365
0$
1!
1"
#366
0"
#367
1$
0!
1"
#368
0"
#369
0$
1!
1"
#370
0"
#371
1$
0!
1"
#372
0"
#373
0$
1!
1"
#374
0"
#375
1$
0!
1"
#376
0"
#377
0$
1!
1"
#378
0"
#379
1$
0!
1"
#380
0"
#381
0$
1!
1"
#382
0"
#383
1$
0!
1"
#384
0"
#385
0$
1!
1"
#386
0"
#387
1$
0!
1"
#388
0"
#389
0$
1!
1"
#390
0"
#391
1$
0!
1"
#392
0"
#393
0$
1!
1"
#394
0"
#395
1$
0!
1"
#396
0"
#397
0$
1!
1"
#398
0"
#399
1$
0!
1"
#400
0"
#401
0$
1!
1"
#402
0"
#403
1$
0!
1"
#404
0"
#405
0$
1!
1"
#406
0"
#407
1$
0!
1"
#408
0"
#409
0$
1!
1"
#410
0"
#411
1$
0!
1"
#412
0"
#413
0$
1!
1"
#414
0"
#415
1$
0!
1"
#416
0"
#417
0$
1!
1"
#418
0"
#419
1$
0!
1"
#420
0"
#421
0$
1!
1"
#422
0"
#423
1$
0!
1"
#424
0"
#425
0$
1!
1"
#426
0"
#427
1$
0!
1"
#428
0"
#429
0$
1!
1"
#430
0"
#431
1$
0!
1"
#432
0"
#433
0$
1!
1"
#434
0"
#435
1$
0!
1"
#436
0"
#437
0$
1!
1"
#438
0"
#439
1$
0!
1"
#440
0"
#441
0$
1!
1"
#442
0"
#443
1$
0!
1"
#444
0"
#445
0$
1!
1"
#446
0"
#447
1$
0!
1"
#448
0"
#449
0$
1!
1"
#450
0"
#451
1$
0!
1"
#452
0"
#453
0$
1!
1"
#454
0"
#455
1$
0!
1"
#456
0"
#457
0$
1!
1"
#458
0"
#459
1$
0!
1"
#460
0"
#461
0$
1!
1"
#462
0"
#463
1$
0!
1"
#464
0"
#465
0$
1!
1"
#466
0"
#467
1$
0!
1"
#468
0"
#469
0$
1!
1"
#470
0"
#471
1$
0!
1"
#472
0"
#473
0$
1!
1"
#474
0"
#475
1$
0!
1"
#476
0"
#477
0$
1!
1"
#478
0"
#479
1$
0!
1"
#480
0"
#481
0$
1!
1"
#482
0"
#483
1$
0!
1"
#484
0"
#485
0$
1!
1"
#486
0"
#487
1$
0!
1"
#488
0"
#489
0$
1!
1"
#490
0"
#491
1$
0!
1"
#492
0"
#493
0$
1!
1"
#494
0"
#495
1$
0!
1"
#496
0"
#497
0$
1!
1"
#498
0"
#499
1$
0!
1"
#500
0"
#501
0$
1!
1"
#502
0"
#503
1$
0!
1"
#504
0"
#505
0$
1!
1"
#506
0"
#507
1$
0!
1"
#508
0"
#509
0$
1!
1"
#510
0"
#511
1$
0!
1"
#512
0"
#513
0$
1!
1"
#514
0"
#515
1$
0!
1"
#516
0"
#517
0$
1!
1"
#518
0"
#519
1$
0!
1"
#520
0"
#521
0$
1!
1"
#522
0"
#523
1$
0!
1"
#524
0"
#525
0$
1!
1"
#526
0"
#527
1$
0!
1"
#528
0"
#529
0$
1!
1"
#530
0"
#531
1$
0!
1"
#532
0"
#533
0$
1!
1"
#534
0"
#535
1$
0!
1"
#536
0"
#537
0$
1!
1"
#538
0"
#539
1$
0!
1"
#540
0"
#541
0$
1!
1"
#542
0"
#543
1$
0!
1"
#544
0"
#545
0$
1!
1"
#546
0"
#547
1$
0!
1"
#548
0"
#549
0$
1!
1"
#550
0"
#551
1$
0!
1"
#552
0"
#553
0$
1!
1"
#554
0"
#555
1$
0!
1"
#556
0"
#557
0$
1!
1"
#558
0"
#559
1$
0!
1"
#560
0"
#561
0$
1!
1"
#562
0"
#563
1$
0!
1"
#564
0"
#565
0$
1!
1"
#566
0"
#567
1$
0!
1"
#568
0"
#569
0$
1!
1"
#570
0"
#571
1$
0!
1"
#572
0"
#573
0$
1!
1"
#574
0"
#575
1$
0!
1"
#576
0"
#577
0$
1!
1"
#578
0"
#579
1$
0!
1"
#580
0"
#581
0$
1!
1"
#582
0"
#583
1$
0!
1"
#584
0"
#585
0$
1!
1"
#586
0"
#587
1$
0!
1"
#588
0"
#589
0$
1!
1"
#590
0"
#591
1$
0!
1"
#592
0"
#593
0$
1!
1"
#594
0"
#595
1$
0!
1"
#596
0"
#597
0$
1!
1"
#598
0"
#599
1$
0!
1"
#600
0"
#601
0$
1!
1"
#602
0"
#603
1$
0!
1"
#604
0"
#605
0$
1!
1"
#606
0"
#607
1$
0!
1"
#608
0"
#609
0$
1!
1"
#610
0"
#611
1$
0!
1"
#612
0"
#613
0$
1!
1"
#614
0"
#615
1$
0!
1"
#616
0"
#617
0$
1!
1"
#618
0"
#619
1$
0!
1"
#620
0"
#621
0$
1!
1"
#622
0"
#623
1$
0!
1"
#624
0"
#625
0$
1!
1"
#626
0"
#627
1$
0!
1"
#628
0"
#629
0$
1!
1"
#630
0"
#631
1$
0!
1"
#632
0"
#633
0$
1!
1"
#634
0"
#635
1$
0!
1"
#636
0"
#637
0$
1!
1"
#638
0"
#639
1$
0!
1"
#640
0"
#641
0$
1!
1"
#642
0"
#643
1$
0!
1"
#644
0"
#645
0$
1!
1"
#646
0"
#647
1$
0!
1"
#648
0"
#649
0$
1!
1"
#650
0"
#651
1$
0!
1"
#652
0"
#653
0$
1!
1"
#654
0"
#655
1$
0!
1"
#656
0"
#657
0$
1!
1"
#658
0"
#659
1$
0!
1"
#660
0"
#661
0$
1!
1"
#662
0"
#663
1$
0!
1"
#664
0"
#665
0$
1!
1"
#666
0"
#667
1$
0!
1"
#668
0"
#669
0$
1!
1"
#670
0"
#671
1$
0!
1"
#672
0"
#673
0$
1!
1"
#674
0"
#675
1$
0!
1"
#676
0"
#677
0$
1!
1"
#678
0"
#679
1$
0!
1"
#680
0"
#681
0$
1!
1"
#682
0"
#683
1$
0!
1"
#684
0"
#685
0$
1!
1"
#686
0"
#687
1$
0!
1"
#688
0"
#689
0$
1!
1"
#690
0"
#691
1$
0!
1"
#692
0"
#693
0$
1!
1"
#694
0"
#695
1$
0!
1"
#696
0"
#697
0$
1!
1"
#698
0"
#699
1$
0!
1"
#700
0"
#701
0$
1!
1"
#702
0"
#703
1$
0!
1"
#704
0"
#705
0$
1!
1"
#706
0"
#707
1$
0!
1"
#708
0"
#709
0$
1!
1"
#710
0"
#711
1$
0!
1"
#712
0"
#713
0$
1!
1"
#714
0"
#715
1$
0!
1"
#716
0"
#717
0$
1!
1"
#718
0"
#719
1$
0!
1"
#720
0"
#721
0$
1!
1"
#722
0"
#723
1$
0!
1"
#724
0"
#725
0$
1!
1"
#726
0"
#727
1$
0!
1"
#728
0"
#729
0$
1!
1"
#730
0"
#731
1$
0!
1"
#732
0"
#733
0$
1!
1"
#734
0"
#735
1$
0!
1"
#736
0"
#737
0$
1!
1"
#738
0"
#739
1$
0!
1"
#740
0"
#741
0$
1!
1"
#742
0"
#743
1$
0!
1"
#744
0"
#745
0$
1!
1"
#746
0"
#747
1$
0!
1"
#748
0"
#749
0$
1!
1"
#750
0"
#751
1$
0!
1"
#752
0"
#753
0$
1!
1"
#754
0"
#755
1$
0!
1"
#756
0"
#757
0$
1!
1"
#758
0"
#759
1$
0!
1"
#760
0"
#761
0$
1!
1"
#762
0"
#763
1$
0!
1"
#764
0"
#765
0$
1!
1"
#766
0"
#767
1$
0!
1"
#768
0"
#769
0$
1!
1"
#770
0"
#771
1$
0!
1"
#772
0"
#773
0$
1!
1"
#774
0"
#775
1$
0!
1"
#776
0"
#777
0$
1!
1"
#778
0"
#779
1$
0!
1"
#780
0"
#781
0$
1!
1"
#782
0"
#783
1$
0!
1"
#784
0"
#785
0$
1!
1"
#786
0"
#787
1$
0!
1"
#788
0"
#789
0$
1!
1"
#790
0"
#791
1$
0!
1"
#792
0"
#793
0$
1!
1"
#794
0"
#795
1$
0!
1"
#796
0"
#797
0$
1!
1"
#798
0"
#799
1$
0!
1"
#800
0"
#801
0$
1!
1"
#802
0"
#803
1$
0!
1"
#804
0"
#805
0$
1!
1"
#806
0"
#807
1$
0!
1"
#808
0"
#809
0$
1!
1"
#810
0"
#811
1$
0!
1"
#812
0"
#813
0$
1!
1"
#814
0"
#815
1$
0!
1"
#816
0"
#817
0$
1!
1"
#818
0"
#819
1$
0!
1"
#820
0"
#821
0$
1!
1"
#822
0"
#823
1$
0!
1"
#824
0"
#825
0$
1!
1"
#826
0"
#827
1$
0!
1"
#828
0"
#829
0$
1!
1"
#830
0"
#831
1$
0!
1"
#832
0"
#833
0$
1!
1"
#834
0"
#835
1$
0!
1"
#836
0"
#837
0$
1!
1"
#838
0"
#839
1$
0!
1"
#840
0"
#841
0$
1!
1"
#842
0"
#843
1$
0!
1"
#844
0"
#845
0$
1!
1"
#846
0"
#847
1$
0!
1"
#848
0"
#849
0$
1!
1"
#850
0"
#851
1$
0!
1"
#852
0"
#853
0$
1!
1"
#854
0"
#855
1$
0!
1"
#856
0"
#857
0$
1!
1"
#858
0"
#859
1$
0!
1"
#860
0"
#861
0$
1!
1"
#862
0"
#863
1$
0!
1"
#864
0"
#865
0$
1!
1"
#866
0"
#867
1$
0!
1"
#868
0"
#869
0$
1!
1"
#870
0"
#871
1$
0!
1"
#872
0"
#873
0$
1!
1"
#874
0"
#875
1$
0!
1"
#876
0"
#877
0$
1!
1"
#878
0"
#879
1$
0!
1"
#880
0"
#881
0$
1!
1"
#882
0"
#883
1$
0!
1"
#884
0"
#885
0$
1!
1"
#886
0"
#887
1$
0!
1"
#888
0"
#889
0$
1!
1"
#890
0"
#891
1$
0!
1"
#892
0"
#893
0$
1!
1"
#894
0"
#895
1$
0!
1"
#896
0"
#897
0$
1!
1"
#898
0"
#899
1$
0!
1"
#900
0"
#901
0$
1!
1"
#902
0"
#903
1$
0!
1"
#904
0"
#905
0$
1!
1"
#906
0"
#907
1$
0!
1"
#908
0"
#909
0$
1!
1"
#910
0"
#911
1$
0!
1"
#912
0"
#913
0$
1!
1"
#914
0"
#915
1$
0!
1"
#916
0"
#917
0$
1!
1"
#918
0"
#919
1$
0!
1"
#920
0"
#921
0$
1!
1"
#922
0"
#923
1$
0!
1"
#924
0"
#925
0$
1!
1"
#926
0"
#927
1$
0!
1"
#928
0"
#929
0$
1!
1"
#930
0"
#931
1$
0!
1"
#932
0"
#933
0$
1!
1"
#934
0"
#935
1$
0!
1"
#936
0"
#937
0$
1!
1"
#938
0"
#939
1$
0!
1"
#940
0"
#941
0$
1!
1"
#942
0"
#943
1$
0!
1"
#944
0"
#945
0$
1!
1"
#946
0"
#947
1$
0!
1"
#948
0"
#949
0$
1!
1"
#950
0"
#951
1$
0!
1"
#952
0"
#953
0$
1!
1"
#954
0"
#955
1$
0!
1"
#956
0"
#957
0$
1!
1"
#958
0"
#959
1$
0!
1"
#960
0"
#961
0$
1!
1"
#962
0"
#963
1$
0!
1"
#964
0"
#965
0$
1!
1"
#966
0"
#967
1$
0!
1"
#968
0"
#969
0$
1!
1"
#970
0"
#971
1$
0!
1"
#972
0"
#973
0$
1!
1"
#974
0"
#975
1$
0!
1"
#976
0"
#977
0$
1!
1"
#978
0"
#979
1$
0!
1"
#980
0"
#981
0$
1!
1"
#982
0"
#983
1$
0!
1"
#984
0"
#985
0$
1!
1"
#986
0"
#987
1$
0!
1"
#988
0"
#989
0$
1!
1"
#990
0"
#991
1$
0!
1"
#992
0"
#993
0$
1!
1"
#994
0"
#995
1$
0!
1"
#996
0"
#997
0$
1!
1"
#998
0"
#999
1$
0!
1"
#1000
0"
#1001
0$
1!
1"
#1002
0"
#1003
1$
0!
1"
#1004
0"
#1005
1"
1#
